{
  "apiSettings": {
    "TYPE": {
      "BASE": 1
    }
  },
  "betType": {
    "1": 0.01,
    "2": 0.02,
    "3": 0.05,
    "4": 0.1,
    "5": 0.2,
    "6": 0.4
  },
  "line": 10,
  "row": 3,
  "column": 5,
  "jackpotUpgradeType": {
    "Major": "Grand",
    "Minor": "Major",
    "Mini": "Minor"
  },
  "separator": "_",
  "upgradeSymbol": "Upgrade",
  "minJackpotSpins": 3,
  "maxJackpotSpins": 12,
  "minimumSymbolOccurrence": {
    "special": {
      "H1": 2
    },
    "base": 3
  },
  "payDirection": {
    "leftToRight": 1
  },
  "symbols": ["H1", "H2", "H3", "H4", "L1", "L2", "L3", "L4", "SCATTER", "BONUS", "WILD"],
  "symbolMultiplier": {
    "H1": {
      "2": 1,
      "3": 5,
      "4": 25,
      "5": 500
    },
    "H2": {
      "2": 0,
      "3": 4,
      "4": 12,
      "5": 70
    },
    "H3": {
      "2": 0,
      "3": 4,
      "4": 12,
      "5": 70
    },
    "H4": {
      "2": 0,
      "3": 2,
      "4": 4,
      "5": 20
    },
    "L1": {
      "2": 0,
      "3": 1,
      "4": 3,
      "5": 15
    },
    "L2": {
      "2": 0,
      "3": 1,
      "4": 3,
      "5": 15
    },
    "L3": {
      "2": 0,
      "3": 1,
      "4": 3,
      "5": 15
    },
    "L4": {
      "2": 0,
      "3": 1,
      "4": 3,
      "5": 15
    },
    "SCATTER": {
      "2": 0,
      "3": 5,
      "4": 20,
      "5": 100
    },
    "BONUS": {
      "2": 0,
      "3": 20,
      "4": 0,
      "5": 0
    }
  },
  "symbolPayType": {
    "line": ["H1", "H2", "H3", "H4", "L1", "L2", "L3", "L4"],
    "scatter": ["SCATTER", "BONUS"]
  },
  "symbolIdMap": {
    "H1": 201,
    "H2": 202,
    "H3": 203,
    "H4": 204,
    "L1": 101,
    "L2": 102,
    "L3": 103,
    "L4": 104,
    "WILD": 80,
    "SCATTER": 25,
    "BONUS": 26
  },
  "specialSymbol": {
    "BONUS": "BONUS",
    "SCATTER": "SCATTER",
    "WILD": "WILD",
    "EXPAND": "EXPAND"
  },
  "patterns": {
    "1": [5, 6, 7, 8, 9],
    "2": [10, 11, 12, 13, 14],
    "3": [0, 1, 2, 3, 4],
    "4": [10, 6, 2, 8, 14],
    "5": [0, 6, 12, 8, 4],
    "6": [10, 11, 7, 3, 4],
    "7": [0, 1, 7, 13, 14],
    "8": [5, 11, 12, 13, 9],
    "9": [0, 6, 7, 8, 4],
    "10": [5, 1, 2, 3, 9]
  },
  "baseGameReelWeights": {
    "B1":69,
    "B2":100
  },
  "reels": {
    "B1": [
      ["L1", "L1", "L1", "SCATTER", "L2", "L2", "L4", "L4", "H4", "H1", "H2", "L1", "L1", "SCATTER", "L2", "L2", "L4", "L4", "L4", "L3", "L3", "H4", "H4", "H4", "L1", "L1", "L1", "L2", "L2", "H3", "H3", "H3", "H3", "L4", "H4", "H2", "H3", "H1", "H4", "H4", "H4", "L4", "L4", "L4", "L3", "L3", "L2", "H1", "L4", "L4", "BONUS", "L3", "L3", "L4", "H4", "L3", "L3", "L3", "H4", "H4", "L2", "H2", "H2", "H4", "H4", "L4", "L4", "L3", "L3", "L3", "L1", "L1", "SCATTER", "L2", "L2", "L2", "L2", "L4", "L4", "L1", "H2", "L1", "L1", "H2", "H2", "H2", "H2", "H2", "L4", "L3", "L3", "L3", "L1", "L1", "SCATTER", "L2", "L2", "L2", "L2", "L3", "L3", "L4", "L4", "BONUS", "L3", "L3", "H4", "H4", "H4", "L1", "L1", "L1", "L2", "L2", "L2", "L1", "L1", "SCATTER", "L2", "L2", "H3", "H3", "H3", "H3", "H3", "L4", "L4", "L4", "L1", "L1", "L1", "L1", "H1", "L2", "L2", "L2", "H4", "H4", "H4", "L3", "L3", "L3", "L4", "L4", "BONUS", "L3", "L3", "L1", "L1", "L1", "H1", "L2", "L2", "L4", "L4", "BONUS", "L3", "L3", "H1", "L4", "L3", "L3", "L3", "L3", "H1", "H4", "L4", "L4", "L4"],
      ["L4", "L4", "L4", "SCATTER", "L3", "L3", "L3", "L2", "L2", "L2", "H3", "H3", "SCATTER", "H3", "H3", "L3", "L4", "L4", "SCATTER", "L3", "L3", "H1", "L4", "L4", "H1", "H4", "H4", "SCATTER", "H4", "H4", "L4", "L4", "H4", "H4", "H4", "H1", "L2", "L2", "L2", "H3", "H3", "WILD", "H3", "H3", "H1", "L2", "L2", "L2", "H1", "L3", "L3", "L3", "L1", "L1", "L1", "L1", "H4", "H4", "WILD", "H4", "H4", "L1", "L1", "L1", "L1", "L1", "L1", "L1", "L1", "L2", "L2", "L2", "L4", "H2", "H2", "H2", "H2", "H2", "L4", "L4", "SCATTER", "L3", "L3", "L3"],
      ["H3", "H4", "L3", "L3", "L3", "L3", "L2", "H2", "SCATTER", "L1", "L1", "L4", "H3", "L4", "L4", "L2", "L2", "BONUS", "L2", "L2", "L4", "L4", "L4", "L4", "L3", "L3", "L3", "H2", "H2", "WILD", "H2", "H2", "L3", "L3", "L3", "H3", "H4", "H2", "H3", "BONUS", "H2", "H3", "H1", "L1", "L1", "L1", "L1", "H3", "L2", "L2", "L2", "WILD", "L2", "L2", "H4", "H2", "H2", "H3", "BONUS", "H2", "H3", "H2", "H2", "SCATTER", "L1", "L1", "L4", "L4", "L4", "H1", "H4", "H3", "H3", "H3", "H3", "H4", "L1", "L1", "L1", "H1"],
      ["L4", "L4", "L4", "L1", "L1", "WILD", "L1", "L1", "L4", "L4", "L4", "SCATTER", "L3", "L3", "L3", "H2", "H2", "WILD", "H2", "H2", "L3", "L3", "L3", "L3", "L2", "L2", "WILD", "L4", "L4", "L4", "L4", "L4", "H4", "H4", "SCATTER", "H4", "H1", "L3", "L3", "L3", "L3", "L2", "L2", "L2", "L2", "H1", "L1", "L1", "WILD", "L1", "L1", "L2", "L2", "L2", "L2", "SCATTER", "H3", "H3", "H3", "H2", "H3", "H3", "H3", "L1", "H2", "SCATTER", "L1", "L1", "H2", "H4", "SCATTER", "H4", "H4", "H4", "H1"],
      ["H4", "H4", "H4", "H4", "L1", "L1", "L1", "H1", "L2", "L2", "L2", "BONUS", "L4", "H3", "H3", "L4", "SCATTER", "L1", "L1", "L4", "H4", "H4", "H3", "H2", "H2", "BONUS", "L2", "L2", "L2", "L2", "H1", "L3", "SCATTER", "L4", "H3", "L4", "L1", "L1", "L1", "H3", "L3", "L2", "L2", "L2", "H3", "L3", "L3", "L3", "H2", "L4", "H1", "L3", "L4", "BONUS", "H3", "L4", "L3", "L3", "L3", "L3", "L3", "L3", "H2", "L4", "H3", "H3", "H3", "H4", "H4", "H4", "H4", "L1", "L1", "L1", "L2", "L2", "L2", "L3", "L4", "L4", "H3", "L4", "H2", "H2", "H2", "H2", "L1", "L1", "L1", "H3", "H3", "H3", "H4", "H4", "H4", "L2", "L2", "L2", "L2", "L3", "L4", "BONUS", "H3", "L4", "L1", "L1", "L1", "L2", "L2", "L2", "H3", "H3", "H3", "H3", "L3", "L3", "SCATTER", "H2", "L4", "H1", "L3", "L4", "BONUS", "H3", "L4", "L3", "L3", "SCATTER", "H2", "L4", "H3", "H3", "H3", "H4", "H4", "H4", "H4", "L1", "L1", "L1", "H3", "L2", "L2", "L2", "L3", "L4", "BONUS", "H3", "L4", "H2", "L1", "L1", "L1", "H3", "H3", "H3", "L4", "H2", "H2", "L4", "H4", "H4", "H4", "L2", "L2", "L2", "L2", "H1", "L3", "L4", "BONUS", "H3", "L4", "L1", "H1", "L2", "L2", "L2", "L1", "H1", "H3", "L3", "L3", "SCATTER", "H2", "L4", "H1", "L3", "L3", "L1", "H1", "L3", "L4", "BONUS", "H3", "L4", "L3", "L3", "SCATTER", "H2", "L4", "H1"]
    ],
    "B2": [
      ["L1", "L1", "L1", "L2", "SCATTER", "H2", "H4", "H2", "H2", "H2", "H2", "L3", "L3", "L3", "H4", "H4", "L1", "L1", "SCATTER", "L2", "L2", "H4", "L3", "L2", "L2", "L4", "L4", "BONUS", "L3", "L3", "H4", "L2", "L1", "L1", "SCATTER", "L2", "L2", "H3", "H3", "H3", "H3", "H3", "L4", "L4", "L4", "BONUS", "L3", "H4", "H4", "L2", "L2", "L2", "L1", "L4", "L4", "BONUS", "L3", "L3", "H1", "H1", "H1", "L1", "L1", "L1", "L2", "L2", "L1", "L4", "BONUS", "L3", "L3", "L4", "L4", "L1", "L3", "L3", "L3", "H1", "H4", "H4", "H4", "L4", "L4", "L4"],
      ["H4", "H4", "H4", "H4", "H1", "L4", "L4", "L4", "L4", "L3", "L3", "L4", "H1", "L2", "L2", "L2", "L4", "L4", "L4", "SCATTER", "L3", "L3", "L4", "L4", "H2", "H2", "H2", "L4", "H4", "H4", "H4", "L2", "L2", "L2", "L2", "L2", "L2", "H1", "H1", "L3", "L3", "L4", "H4", "H4", "H4", "H4", "SCATTER", "H2", "L1", "L1", "L1", "L1", "H1", "L1", "L1", "L1", "H3", "H3", "H3", "H3", "H3", "L1", "L4", "L3", "L2", "L2", "L2", "H2", "L1", "L1", "SCATTER", "L3", "L3", "L3", "L1", "L3", "L3"],
      ["H3", "H3", "L3", "L3", "L3", "H4", "H4", "L2", "L2", "H2", "SCATTER", "L1", "L1", "H1", "H1", "L4", "L4", "L4", "H3", "L4", "L4", "H4", "L3", "L3", "L3", "L3", "H2", "H2", "H3", "H2", "H4", "H3", "H2", "H2", "L4", "L4", "BONUS", "L3", "L3", "H1", "H3", "SCATTER", "H4", "H4", "L1", "L1", "L1", "L2", "L2", "L2", "L2", "L2", "L2", "L2", "H2", "H3", "BONUS", "H2", "H3", "H2", "H2", "H2", "L2", "H2", "SCATTER", "L1", "L1", "L4", "L4", "L4", "H3", "H3", "H3", "H3", "L1", "L1", "L1"],
      ["SCATTER", "L4", "H4", "L4", "L4", "L4", "L4", "H1", "H1", "L3", "L3", "L3", "SCATTER", "L3", "L3", "L3", "L3", "H2", "H2", "H2", "H4", "L2", "L2", "L2", "L1", "H1", "L4", "L4", "L4", "SCATTER", "L4", "L4", "H4", "L3", "H3", "L3", "L3", "L3", "L2", "L2", "H1", "L2", "H4", "L2", "L2", "L2", "L2", "H3", "H3", "H3", "H3", "H4", "SCATTER", "L1", "L1", "L1", "H2", "H2", "H2", "H3", "H4", "L1", "L1", "L1", "H2", "SCATTER", "L1", "L1", "L1", "H4", "H3", "H4"],
      ["H4", "H4", "H4", "H4", "L1", "L1", "L1", "L2", "L2", "L2", "L3", "L4", "BONUS", "H3", "L4", "H2", "H4", "BONUS", "H2", "H3", "H3", "H3", "H4", "BONUS", "L2", "L2", "L2", "H4", "L3", "L4", "BONUS", "H3", "L4", "L1", "L1", "L1", "H2", "L2", "L2", "L2", "H3", "H3", "H3", "H3", "L3", "L3", "SCATTER", "H2", "L4", "L3", "H1", "H1", "H1", "L3", "L4", "BONUS", "H3", "L4", "L3", "L3", "L3", "H2", "H2", "BONUS", "L4", "L1", "L1"]
    ]
  },
  "jackpotStartupAndIncrementValues": {
    "Grand": {
      "value": 5000,
      "increment": 0.005
    },
    "Major": {
      "value": 2000,
      "increment": 0.005
    },
    "Minor": {
      "value": 1000,
      "increment": 0.005
    },
    "Mini": {
      "value": 200,
      "increment": 0.005
    }
  },
  "jackpotPickupWeightValues": {
    "1": {
      "Grand_1": 2700,
      "Grand_2": 60,
      "Grand_3": 5,
      "Major_1": 3750,
      "Major_2": 700,
      "Major_3": 50,
      "Minor_1": 7000,
      "Minor_2": 1580,
      "Minor_3": 120,
      "Mini_1": 10000,
      "Mini_2": 4500,
      "Mini_3": 1000,
      "Major_Upgrade": 5,
      "Minor_Upgrade": 5,
      "Mini_Upgrade": 5
    },
    "2": {
      "Grand_1": 2950,
      "Grand_2": 70,
      "Grand_3": 10,
      "Major_1": 4000,
      "Major_2": 800,
      "Major_3": 70,
      "Minor_1": 7200,
      "Minor_2": 1580,
      "Minor_3": 110,
      "Mini_1": 9750,
      "Mini_2": 4100,
      "Mini_3": 1000,
      "Major_Upgrade": 70,
      "Minor_Upgrade": 500,
      "Mini_Upgrade": 200
    },
    "3": {
      "Grand_1": 2950,
      "Grand_2": 70,
      "Grand_3": 10,
      "Major_1": 4000,
      "Major_2": 800,
      "Major_3": 70,
      "Minor_1": 7200,
      "Minor_2": 1580,
      "Minor_3": 150,
      "Mini_1": 9750,
      "Mini_2": 4100,
      "Mini_3": 950,
      "MajorUpgrade": 70,
      "MinorUpgrade": 500,
      "MiniUpgrade": 190
    },
    "4": {
      "Grand_1": 3000,
      "Grand_2": 60,
      "Grand_3": 5,
      "Major_1": 4000,
      "Major_2": 780,
      "Major_3": 50,
      "Minor_1": 7000,
      "Minor_2": 1500,
      "Minor_3": 120,
      "Mini_1": 10000,
      "Mini_2": 4000,
      "Mini_3": 800,
      "Major_Upgrade": 70,
      "Minor_Upgrade": 500,
      "Mini_Upgrade": 100
    },
    "5": {
      "Grand_1": 3000,
      "Grand_2": 60,
      "Grand_3": 5,
      "Major_1": 4000,
      "Major_2": 780,
      "Major_3": 55,
      "Minor_1": 7000,
      "Minor_2": 1500,
      "Minor_3": 120,
      "Mini_1": 10000,
      "Mini_2": 4000,
      "Mini_3": 795,
      "Major_Upgrade": 70,
      "Minor_Upgrade": 500,
      "Mini_Upgrade": 100
    },
    "6": {
      "Grand_1": 3000,
      "Grand_2": 90,
      "Grand_3": 20,
      "Major_1": 4000,
      "Major_2": 780,
      "Major_3": 65,
      "Minor_1": 7500,
      "Minor_2": 1500,
      "Minor_3": 200,
      "Mini_1": 9500,
      "Mini_2": 3790,
      "Mini_3": 700,
      "Major_Upgrade": 70,
      "Minor_Upgrade": 500,
      "Mini_Upgrade": 270
    }
  },
  "jackpotBetTriggerWeights": {
    "1": {
      "0": 40000,
      "1": 1
    },
    "2": {
      "0": 20500,
      "1": 1
    },
    "3": {
      "0": 5850,
      "1": 1
    },
    "4": {
      "0": 2395,
      "1": 1
    },
    "5": {
      "0": 1150,
      "1": 1
    },
    "6": {
      "0": 800,
      "1": 1
    }
  },
  "gambleColors": {
    "Heart":1,
    "Diamond":1,
    "Spade":2,
    "Club":2
  },
  "gambleWeights": {
    "Heart":1,
    "Diamond":1,
    "Spade":1,
    "Club":1
  }
}
